{
    "code": 0,
    "msg": "",
    "data": {
        "heroList": [
            {
                "heroId": 166,
                "heroName": "Arthur",
                "icon": "https://raw.githubusercontent.com/tikliz/hok_draft_utils/refs/heads/main/res/heros/Images/image_hero_head-Arthur.png",
                "mainJob": 2,
                "recommendRoad": 1,
                "minorJob": 1,
                "mainJobName": "Guerreiro",
                "minorJobName": "Tanque",
                "recommendRoadName": "Rota superior",
                "firstTimeUpgradeSkill": 2,
                "cover": ""
            },
            {
                "heroId": 112,
                "heroName": "Luban No.7",
                "icon": "https://raw.githubusercontent.com/tikliz/hok_draft_utils/refs/heads/main/res/heros/Images/image_hero_head-Luban No.7.png",
                "mainJob": 5,
                "recommendRoad": 5,
                "minorJob": 0,
                "mainJobName": "Atirador",
                "minorJobName": "",
                "recommendRoadName": "Rota inferior",
                "firstTimeUpgradeSkill": 2,
                "cover": ""
            },
            {
                "heroId": 105,
                "heroName": "Lian Po",
                "icon": "https://raw.githubusercontent.com/tikliz/hok_draft_utils/refs/heads/main/res/heros/Images/image_hero_head-Lian Po.png",
                "mainJob": 1,
                "recommendRoad": 1,
                "minorJob": 0,
                "mainJobName": "Tanque",
                "minorJobName": "",
                "recommendRoadName": "Rota superior",
                "firstTimeUpgradeSkill": 2,
                "cover": ""
            },
            {
                "heroId": 106,
                "heroName": "Xiao Qiao",
                "icon": "https://raw.githubusercontent.com/tikliz/hok_draft_utils/refs/heads/main/res/heros/Images/image_hero_head-Xiao Qiao.png",
                "mainJob": 4,
                "recommendRoad": 3,
                "minorJob": 0,
                "mainJobName": "Mago",
                "minorJobName": "",
                "recommendRoadName": "Rota do meio",
                "firstTimeUpgradeSkill": 1,
                "cover": ""
            },
            {
                "heroId": 522,
                "heroName": "Yao",
                "icon": "https://raw.githubusercontent.com/tikliz/hok_draft_utils/refs/heads/main/res/heros/Images/image_hero_head-Yao.png",
                "mainJob": 2,
                "recommendRoad": 2,
                "minorJob": 0,
                "mainJobName": "Guerreiro",
                "minorJobName": "",
                "recommendRoadName": "Caça",
                "firstTimeUpgradeSkill": 1,
                "cover": ""
            },
            {
                "heroId": 153,
                "heroName": "Príncipe de Lanling",
                "icon": "https://raw.githubusercontent.com/tikliz/hok_draft_utils/refs/heads/main/res/heros/Images/image_hero_head-Príncipe de Lanling.png",
                "mainJob": 3,
                "recommendRoad": 2,
                "minorJob": 0,
                "mainJobName": "Assassino",
                "minorJobName": "",
                "recommendRoadName": "Caça",
                "firstTimeUpgradeSkill": 1,
                "cover": ""
            },
            {
                "heroId": 118,
                "heroName": "Sun Bin",
                "icon": "https://raw.githubusercontent.com/tikliz/hok_draft_utils/refs/heads/main/res/heros/Images/image_hero_head-Sun Bin.png",
                "mainJob": 6,
                "recommendRoad": 4,
                "minorJob": 4,
                "mainJobName": "Suporte",
                "minorJobName": "Mago",
                "recommendRoadName": "Apoio",
                "firstTimeUpgradeSkill": 1,
                "cover": ""
            },
            {
                "heroId": 107,
                "heroName": "Zilong",
                "icon": "https://raw.githubusercontent.com/tikliz/hok_draft_utils/refs/heads/main/res/heros/Images/image_hero_head-Zilong.png",
                "mainJob": 2,
                "recommendRoad": 2,
                "minorJob": 3,
                "mainJobName": "Guerreiro",
                "minorJobName": "Assassino",
                "recommendRoadName": "Caça",
                "firstTimeUpgradeSkill": 2,
                "cover": ""
            },
            {
                "heroId": 108,
                "heroName": "Mozi",
                "icon": "https://raw.githubusercontent.com/tikliz/hok_draft_utils/refs/heads/main/res/heros/Images/image_hero_head-Mozi.png",
                "mainJob": 4,
                "recommendRoad": 3,
                "minorJob": 2,
                "mainJobName": "Mago",
                "minorJobName": "Guerreiro",
                "recommendRoadName": "Rota do meio",
                "firstTimeUpgradeSkill": 2,
                "cover": ""
            },
            {
                "heroId": 124,
                "heroName": "Zhou Yu",
                "icon": "https://raw.githubusercontent.com/tikliz/hok_draft_utils/refs/heads/main/res/heros/Images/image_hero_head-Zhou Yu.png",
                "mainJob": 4,
                "recommendRoad": 3,
                "minorJob": 0,
                "mainJobName": "Mago",
                "minorJobName": "",
                "recommendRoadName": "Rota do meio",
                "firstTimeUpgradeSkill": 2,
                "cover": ""
            },
            {
                "heroId": 111,
                "heroName": "Lady Sun",
                "icon": "https://raw.githubusercontent.com/tikliz/hok_draft_utils/refs/heads/main/res/heros/Images/image_hero_head-Lady Sun.png",
                "mainJob": 5,
                "recommendRoad": 5,
                "minorJob": 0,
                "mainJobName": "Atirador",
                "minorJobName": "",
                "recommendRoadName": "Rota inferior",
                "firstTimeUpgradeSkill": 1,
                "cover": ""
            },
            {
                "heroId": 114,
                "heroName": "Liu Shan",
                "icon": "https://raw.githubusercontent.com/tikliz/hok_draft_utils/refs/heads/main/res/heros/Images/image_hero_head-Liu Shan.png",
                "mainJob": 6,
                "recommendRoad": 4,
                "minorJob": 1,
                "mainJobName": "Suporte",
                "minorJobName": "Tanque",
                "recommendRoadName": "Apoio",
                "firstTimeUpgradeSkill": 1,
                "cover": ""
            },
            {
                "heroId": 109,
                "heroName": "Daji",
                "icon": "https://raw.githubusercontent.com/tikliz/hok_draft_utils/refs/heads/main/res/heros/Images/image_hero_head-Daji.png",
                "mainJob": 4,
                "recommendRoad": 3,
                "minorJob": 0,
                "mainJobName": "Mago",
                "minorJobName": "",
                "recommendRoadName": "Rota do meio",
                "firstTimeUpgradeSkill": 1,
                "cover": ""
            },
            {
                "heroId": 113,
                "heroName": "Zhuangzi",
                "icon": "https://raw.githubusercontent.com/tikliz/hok_draft_utils/refs/heads/main/res/heros/Images/image_hero_head-Zhuangzi.png",
                "mainJob": 6,
                "recommendRoad": 4,
                "minorJob": 1,
                "mainJobName": "Suporte",
                "minorJobName": "Tanque",
                "recommendRoadName": "Apoio",
                "firstTimeUpgradeSkill": 1,
                "cover": ""
            },
            {
                "heroId": 115,
                "heroName": "Gao",
                "icon": "https://raw.githubusercontent.com/tikliz/hok_draft_utils/refs/heads/main/res/heros/Images/image_hero_head-Gao.png",
                "mainJob": 4,
                "recommendRoad": 3,
                "minorJob": 0,
                "mainJobName": "Mago",
                "minorJobName": "",
                "recommendRoadName": "Rota do meio",
                "firstTimeUpgradeSkill": 1,
                "cover": ""
            },
            {
                "heroId": 117,
                "heroName": "Wuyan",
                "icon": "https://raw.githubusercontent.com/tikliz/hok_draft_utils/refs/heads/main/res/heros/Images/image_hero_head-Wuyan.png",
                "mainJob": 2,
                "recommendRoad": 1,
                "minorJob": 1,
                "mainJobName": "Guerreiro",
                "minorJobName": "Tanque",
                "recommendRoadName": "Rota superior",
                "firstTimeUpgradeSkill": 2,
                "cover": ""
            },
            {
                "heroId": 119,
                "heroName": "Dr. Bian",
                "icon": "https://raw.githubusercontent.com/tikliz/hok_draft_utils/refs/heads/main/res/heros/Images/image_hero_head-Dr. Bian.png",
                "mainJob": 4,
                "recommendRoad": 3,
                "minorJob": 0,
                "mainJobName": "Mago",
                "minorJobName": "",
                "recommendRoadName": "Rota do meio",
                "firstTimeUpgradeSkill": 1,
                "cover": ""
            },
            {
                "heroId": 150,
                "heroName": "Han Xin",
                "icon": "https://raw.githubusercontent.com/tikliz/hok_draft_utils/refs/heads/main/res/heros/Images/image_hero_head-Han Xin.png",
                "mainJob": 3,
                "recommendRoad": 2,
                "minorJob": 0,
                "mainJobName": "Assassino",
                "minorJobName": "",
                "recommendRoadName": "Caça",
                "firstTimeUpgradeSkill": 1,
                "cover": ""
            },
            {
                "heroId": 169,
                "heroName": "Hou Yi",
                "icon": "https://raw.githubusercontent.com/tikliz/hok_draft_utils/refs/heads/main/res/heros/Images/image_hero_head-Hou Yi.png",
                "mainJob": 5,
                "recommendRoad": 5,
                "minorJob": 0,
                "mainJobName": "Atirador",
                "minorJobName": "",
                "recommendRoadName": "Rota inferior",
                "firstTimeUpgradeSkill": 2,
                "cover": ""
            },
            {
                "heroId": 123,
                "heroName": "Lu Bu",
                "icon": "https://raw.githubusercontent.com/tikliz/hok_draft_utils/refs/heads/main/res/heros/Images/image_hero_head-Lu Bu.png",
                "mainJob": 2,
                "recommendRoad": 1,
                "minorJob": 1,
                "mainJobName": "Guerreiro",
                "minorJobName": "Tanque",
                "recommendRoadName": "Rota superior",
                "firstTimeUpgradeSkill": 1,
                "cover": ""
            },
            {
                "heroId": 126,
                "heroName": "Dun",
                "icon": "https://raw.githubusercontent.com/tikliz/hok_draft_utils/refs/heads/main/res/heros/Images/image_hero_head-Dun.png",
                "mainJob": 1,
                "recommendRoad": 1,
                "minorJob": 2,
                "mainJobName": "Tanque",
                "minorJobName": "Guerreiro",
                "recommendRoadName": "Rota superior",
                "firstTimeUpgradeSkill": 1,
                "cover": ""
            },
            {
                "heroId": 127,
                "heroName": "Lady Zhen",
                "icon": "https://raw.githubusercontent.com/tikliz/hok_draft_utils/refs/heads/main/res/heros/Images/image_hero_head-Lady Zhen.png",
                "mainJob": 4,
                "recommendRoad": 3,
                "minorJob": 0,
                "mainJobName": "Mago",
                "minorJobName": "",
                "recommendRoadName": "Rota do meio",
                "firstTimeUpgradeSkill": 2,
                "cover": ""
            },
            {
                "heroId": 182,
                "heroName": "Gan & Mo",
                "icon": "https://raw.githubusercontent.com/tikliz/hok_draft_utils/refs/heads/main/res/heros/Images/image_hero_head-Gan & Mo.png",
                "mainJob": 4,
                "recommendRoad": 3,
                "minorJob": 0,
                "mainJobName": "Mago",
                "minorJobName": "",
                "recommendRoadName": "Rota do meio",
                "firstTimeUpgradeSkill": 2,
                "cover": ""
            },
            {
                "heroId": 129,
                "heroName": "Dian Wei",
                "icon": "https://raw.githubusercontent.com/tikliz/hok_draft_utils/refs/heads/main/res/heros/Images/image_hero_head-Dian Wei.png",
                "mainJob": 2,
                "recommendRoad": 2,
                "minorJob": 0,
                "mainJobName": "Guerreiro",
                "minorJobName": "",
                "recommendRoadName": "Caça",
                "firstTimeUpgradeSkill": 2,
                "cover": ""
            },
            {
                "heroId": 130,
                "heroName": "Musashi",
                "icon": "https://raw.githubusercontent.com/tikliz/hok_draft_utils/refs/heads/main/res/heros/Images/image_hero_head-Musashi.png",
                "mainJob": 2,
                "recommendRoad": 2,
                "minorJob": 0,
                "mainJobName": "Guerreiro",
                "minorJobName": "",
                "recommendRoadName": "Caça",
                "firstTimeUpgradeSkill": 2,
                "cover": ""
            },
            {
                "heroId": 131,
                "heroName": "Li Bai",
                "icon": "https://raw.githubusercontent.com/tikliz/hok_draft_utils/refs/heads/main/res/heros/Images/image_hero_head-Li Bai.png",
                "mainJob": 3,
                "recommendRoad": 2,
                "minorJob": 0,
                "mainJobName": "Assassino",
                "minorJobName": "",
                "recommendRoadName": "Caça",
                "firstTimeUpgradeSkill": 2,
                "cover": ""
            },
            {
                "heroId": 170,
                "heroName": "Liu Bei",
                "icon": "https://raw.githubusercontent.com/tikliz/hok_draft_utils/refs/heads/main/res/heros/Images/image_hero_head-Liu Bei.png",
                "mainJob": 2,
                "recommendRoad": 2,
                "minorJob": 0,
                "mainJobName": "Guerreiro",
                "minorJobName": "",
                "recommendRoadName": "Caça",
                "firstTimeUpgradeSkill": 1,
                "cover": ""
            },
            {
                "heroId": 132,
                "heroName": "Marco Polo",
                "icon": "https://raw.githubusercontent.com/tikliz/hok_draft_utils/refs/heads/main/res/heros/Images/image_hero_head-Marco Polo.png",
                "mainJob": 5,
                "recommendRoad": 5,
                "minorJob": 0,
                "mainJobName": "Atirador",
                "minorJobName": "",
                "recommendRoadName": "Rota inferior",
                "firstTimeUpgradeSkill": 1,
                "cover": ""
            },
            {
                "heroId": 133,
                "heroName": "Di Renjie",
                "icon": "https://raw.githubusercontent.com/tikliz/hok_draft_utils/refs/heads/main/res/heros/Images/image_hero_head-Di Renjie.png",
                "mainJob": 5,
                "recommendRoad": 5,
                "minorJob": 0,
                "mainJobName": "Atirador",
                "minorJobName": "",
                "recommendRoadName": "Rota inferior",
                "firstTimeUpgradeSkill": 1,
                "cover": ""
            },
            {
                "heroId": 134,
                "heroName": "Dharma",
                "icon": "https://raw.githubusercontent.com/tikliz/hok_draft_utils/refs/heads/main/res/heros/Images/image_hero_head-Dharma.png",
                "mainJob": 2,
                "recommendRoad": 1,
                "minorJob": 1,
                "mainJobName": "Guerreiro",
                "minorJobName": "Tanque",
                "recommendRoadName": "Rota superior",
                "firstTimeUpgradeSkill": 2,
                "cover": ""
            },
            {
                "heroId": 148,
                "heroName": "Ziya",
                "icon": "https://raw.githubusercontent.com/tikliz/hok_draft_utils/refs/heads/main/res/heros/Images/image_hero_head-Ziya.png",
                "mainJob": 4,
                "recommendRoad": 3,
                "minorJob": 0,
                "mainJobName": "Mago",
                "minorJobName": "",
                "recommendRoadName": "Rota do meio",
                "firstTimeUpgradeSkill": 1,
                "cover": ""
            },
            {
                "heroId": 135,
                "heroName": "Xiang Yu",
                "icon": "https://raw.githubusercontent.com/tikliz/hok_draft_utils/refs/heads/main/res/heros/Images/image_hero_head-Xiang Yu.png",
                "mainJob": 1,
                "recommendRoad": 1,
                "minorJob": 0,
                "mainJobName": "Tanque",
                "minorJobName": "",
                "recommendRoadName": "Rota superior",
                "firstTimeUpgradeSkill": 1,
                "cover": ""
            },
            {
                "heroId": 517,
                "heroName": "Augran",
                "icon": "https://raw.githubusercontent.com/tikliz/hok_draft_utils/refs/heads/main/res/heros/Images/image_hero_head-Augran.png",
                "mainJob": 2,
                "recommendRoad": 2,
                "minorJob": 0,
                "mainJobName": "Guerreiro",
                "minorJobName": "",
                "recommendRoadName": "Caça",
                "firstTimeUpgradeSkill": 2,
                "cover": ""
            },
            {
                "heroId": 174,
                "heroName": "Consorte Yu",
                "icon": "https://raw.githubusercontent.com/tikliz/hok_draft_utils/refs/heads/main/res/heros/Images/image_hero_head-Consorte Yu.png",
                "mainJob": 5,
                "recommendRoad": 5,
                "minorJob": 0,
                "mainJobName": "Atirador",
                "minorJobName": "",
                "recommendRoadName": "Rota inferior",
                "firstTimeUpgradeSkill": 1,
                "cover": ""
            },
            {
                "heroId": 137,
                "heroName": "Sima Yi",
                "icon": "https://raw.githubusercontent.com/tikliz/hok_draft_utils/refs/heads/main/res/heros/Images/image_hero_head-Sima Yi.png",
                "mainJob": 3,
                "recommendRoad": 2,
                "minorJob": 4,
                "mainJobName": "Assassino",
                "minorJobName": "Mago",
                "recommendRoadName": "Caça",
                "firstTimeUpgradeSkill": 1,
                "cover": ""
            },
            {
                "heroId": 139,
                "heroName": "Fuzi",
                "icon": "https://raw.githubusercontent.com/tikliz/hok_draft_utils/refs/heads/main/res/heros/Images/image_hero_head-Fuzi.png",
                "mainJob": 2,
                "recommendRoad": 1,
                "minorJob": 0,
                "mainJobName": "Guerreiro",
                "minorJobName": "",
                "recommendRoadName": "Rota superior",
                "firstTimeUpgradeSkill": 2,
                "cover": ""
            },
            {
                "heroId": 162,
                "heroName": "Nakoruru",
                "icon": "https://raw.githubusercontent.com/tikliz/hok_draft_utils/refs/heads/main/res/heros/Images/image_hero_head-Nakoruru.png",
                "mainJob": 3,
                "recommendRoad": 2,
                "minorJob": 0,
                "mainJobName": "Assassino",
                "minorJobName": "",
                "recommendRoadName": "Caça",
                "firstTimeUpgradeSkill": 2,
                "cover": ""
            },
            {
                "heroId": 157,
                "heroName": "Mai Shiranui",
                "icon": "https://raw.githubusercontent.com/tikliz/hok_draft_utils/refs/heads/main/res/heros/Images/image_hero_head-Mai Shiranui.png",
                "mainJob": 4,
                "recommendRoad": 3,
                "minorJob": 3,
                "mainJobName": "Mago",
                "minorJobName": "Assassino",
                "recommendRoadName": "Rota do meio",
                "firstTimeUpgradeSkill": 2,
                "cover": ""
            },
            {
                "heroId": 140,
                "heroName": "Guan Yu",
                "icon": "https://raw.githubusercontent.com/tikliz/hok_draft_utils/refs/heads/main/res/heros/Images/image_hero_head-Guan Yu.png",
                "mainJob": 2,
                "recommendRoad": 1,
                "minorJob": 0,
                "mainJobName": "Guerreiro",
                "minorJobName": "",
                "recommendRoadName": "Rota superior",
                "firstTimeUpgradeSkill": 1,
                "cover": ""
            },
            {
                "heroId": 146,
                "heroName": "Luna",
                "icon": "https://raw.githubusercontent.com/tikliz/hok_draft_utils/refs/heads/main/res/heros/Images/image_hero_head-Luna.png",
                "mainJob": 2,
                "recommendRoad": 2,
                "minorJob": 4,
                "mainJobName": "Guerreiro",
                "minorJobName": "Mago",
                "recommendRoadName": "Caça",
                "firstTimeUpgradeSkill": 1,
                "cover": ""
            },
            {
                "heroId": 141,
                "heroName": "Diaochan",
                "icon": "https://raw.githubusercontent.com/tikliz/hok_draft_utils/refs/heads/main/res/heros/Images/image_hero_head-Diaochan.png",
                "mainJob": 4,
                "recommendRoad": 3,
                "minorJob": 3,
                "mainJobName": "Mago",
                "minorJobName": "Assassino",
                "recommendRoadName": "Rota do meio",
                "firstTimeUpgradeSkill": 1,
                "cover": ""
            },
            {
                "heroId": 142,
                "heroName": "Angela",
                "icon": "https://raw.githubusercontent.com/tikliz/hok_draft_utils/refs/heads/main/res/heros/Images/image_hero_head-Angela.png",
                "mainJob": 4,
                "recommendRoad": 3,
                "minorJob": 0,
                "mainJobName": "Mago",
                "minorJobName": "",
                "recommendRoadName": "Rota do meio",
                "firstTimeUpgradeSkill": 1,
                "cover": ""
            },
            {
                "heroId": 154,
                "heroName": "Mulan",
                "icon": "https://raw.githubusercontent.com/tikliz/hok_draft_utils/refs/heads/main/res/heros/Images/image_hero_head-Mulan.png",
                "mainJob": 2,
                "recommendRoad": 1,
                "minorJob": 3,
                "mainJobName": "Guerreiro",
                "minorJobName": "Assassino",
                "recommendRoadName": "Rota superior",
                "firstTimeUpgradeSkill": 1,
                "cover": ""
            },
            {
                "heroId": 149,
                "heroName": "Liu Bang",
                "icon": "https://raw.githubusercontent.com/tikliz/hok_draft_utils/refs/heads/main/res/heros/Images/image_hero_head-Liu Bang.png",
                "mainJob": 1,
                "recommendRoad": 1,
                "minorJob": 4,
                "mainJobName": "Tanque",
                "minorJobName": "Mago",
                "recommendRoadName": "Rota superior",
                "firstTimeUpgradeSkill": 1,
                "cover": ""
            },
            {
                "heroId": 533,
                "heroName": "Agu",
                "icon": "https://raw.githubusercontent.com/tikliz/hok_draft_utils/refs/heads/main/res/heros/Images/image_hero_head-Agu.png",
                "mainJob": 1,
                "recommendRoad": 2,
                "minorJob": 0,
                "mainJobName": "Tanque",
                "minorJobName": "",
                "recommendRoadName": "Caça",
                "firstTimeUpgradeSkill": 2,
                "cover": ""
            },
            {
                "heroId": 152,
                "heroName": "Princesa Gélida",
                "icon": "https://raw.githubusercontent.com/tikliz/hok_draft_utils/refs/heads/main/res/heros/Images/image_hero_head-Princesa Gélida.png",
                "mainJob": 4,
                "recommendRoad": 3,
                "minorJob": 0,
                "mainJobName": "Mago",
                "minorJobName": "",
                "recommendRoadName": "Rota do meio",
                "firstTimeUpgradeSkill": 1,
                "cover": ""
            },
            {
                "heroId": 178,
                "heroName": "Yang Jian",
                "icon": "https://raw.githubusercontent.com/tikliz/hok_draft_utils/refs/heads/main/res/heros/Images/image_hero_head-Yang Jian.png",
                "mainJob": 2,
                "recommendRoad": 1,
                "minorJob": 0,
                "mainJobName": "Guerreiro",
                "minorJobName": "",
                "recommendRoadName": "Rota superior",
                "firstTimeUpgradeSkill": 2,
                "cover": ""
            },
            {
                "heroId": 173,
                "heroName": "Fang",
                "icon": "https://raw.githubusercontent.com/tikliz/hok_draft_utils/refs/heads/main/res/heros/Images/image_hero_head-Fang.png",
                "mainJob": 5,
                "recommendRoad": 5,
                "minorJob": 0,
                "mainJobName": "Atirador",
                "minorJobName": "",
                "recommendRoadName": "Rota inferior",
                "firstTimeUpgradeSkill": 1,
                "cover": ""
            },
            {
                "heroId": 156,
                "heroName": "Liang",
                "icon": "https://raw.githubusercontent.com/tikliz/hok_draft_utils/refs/heads/main/res/heros/Images/image_hero_head-Liang.png",
                "mainJob": 4,
                "recommendRoad": 3,
                "minorJob": 0,
                "mainJobName": "Mago",
                "minorJobName": "",
                "recommendRoadName": "Rota do meio",
                "firstTimeUpgradeSkill": 2,
                "cover": ""
            },
            {
                "heroId": 163,
                "heroName": "Ukyo Tachibana",
                "icon": "https://raw.githubusercontent.com/tikliz/hok_draft_utils/refs/heads/main/res/heros/Images/image_hero_head-Ukyo Tachibana.png",
                "mainJob": 3,
                "recommendRoad": 2,
                "minorJob": 2,
                "mainJobName": "Assassino",
                "minorJobName": "Guerreiro",
                "recommendRoadName": "Caça",
                "firstTimeUpgradeSkill": 1,
                "cover": ""
            },
            {
                "heroId": 180,
                "heroName": "Nezha",
                "icon": "https://raw.githubusercontent.com/tikliz/hok_draft_utils/refs/heads/main/res/heros/Images/image_hero_head-Nezha.png",
                "mainJob": 2,
                "recommendRoad": 1,
                "minorJob": 0,
                "mainJobName": "Guerreiro",
                "minorJobName": "",
                "recommendRoadName": "Rota superior",
                "firstTimeUpgradeSkill": 1,
                "cover": ""
            },
            {
                "heroId": 167,
                "heroName": "Wukong",
                "icon": "https://raw.githubusercontent.com/tikliz/hok_draft_utils/refs/heads/main/res/heros/Images/image_hero_head-Wukong.png",
                "mainJob": 3,
                "recommendRoad": 2,
                "minorJob": 2,
                "mainJobName": "Assassino",
                "minorJobName": "Guerreiro",
                "recommendRoadName": "Caça",
                "firstTimeUpgradeSkill": 2,
                "cover": ""
            },
            {
                "heroId": 171,
                "heroName": "Zhang Fei",
                "icon": "https://raw.githubusercontent.com/tikliz/hok_draft_utils/refs/heads/main/res/heros/Images/image_hero_head-Zhang Fei.png",
                "mainJob": 6,
                "recommendRoad": 4,
                "minorJob": 1,
                "mainJobName": "Suporte",
                "minorJobName": "Tanque",
                "recommendRoadName": "Apoio",
                "firstTimeUpgradeSkill": 1,
                "cover": ""
            },
            {
                "heroId": 175,
                "heroName": "Kui",
                "icon": "https://raw.githubusercontent.com/tikliz/hok_draft_utils/refs/heads/main/res/heros/Images/image_hero_head-Kui.png",
                "mainJob": 6,
                "recommendRoad": 4,
                "minorJob": 4,
                "mainJobName": "Suporte",
                "minorJobName": "Mago",
                "recommendRoadName": "Apoio",
                "firstTimeUpgradeSkill": 2,
                "cover": ""
            },
            {
                "heroId": 176,
                "heroName": "Yuhuan",
                "icon": "https://raw.githubusercontent.com/tikliz/hok_draft_utils/refs/heads/main/res/heros/Images/image_hero_head-Yuhuan.png",
                "mainJob": 4,
                "recommendRoad": 3,
                "minorJob": 0,
                "mainJobName": "Mago",
                "minorJobName": "",
                "recommendRoadName": "Rota do meio",
                "firstTimeUpgradeSkill": 1,
                "cover": ""
            },
            {
                "heroId": 503,
                "heroName": "Biron",
                "icon": "https://raw.githubusercontent.com/tikliz/hok_draft_utils/refs/heads/main/res/heros/Images/image_hero_head-Biron.png",
                "mainJob": 2,
                "recommendRoad": 1,
                "minorJob": 0,
                "mainJobName": "Guerreiro",
                "minorJobName": "",
                "recommendRoadName": "Rota superior",
                "firstTimeUpgradeSkill": 1,
                "cover": ""
            },
            {
                "heroId": 179,
                "heroName": "Nuwa",
                "icon": "https://raw.githubusercontent.com/tikliz/hok_draft_utils/refs/heads/main/res/heros/Images/image_hero_head-Nuwa.png",
                "mainJob": 4,
                "recommendRoad": 3,
                "minorJob": 0,
                "mainJobName": "Mago",
                "minorJobName": "",
                "recommendRoadName": "Rota do meio",
                "firstTimeUpgradeSkill": 1,
                "cover": ""
            },
            {
                "heroId": 183,
                "heroName": "Athena",
                "icon": "https://raw.githubusercontent.com/tikliz/hok_draft_utils/refs/heads/main/res/heros/Images/image_hero_head-Athena.png",
                "mainJob": 2,
                "recommendRoad": 2,
                "minorJob": 0,
                "mainJobName": "Guerreiro",
                "minorJobName": "",
                "recommendRoadName": "Caça",
                "firstTimeUpgradeSkill": 2,
                "cover": ""
            },
            {
                "heroId": 193,
                "heroName": "Kaizer",
                "icon": "https://raw.githubusercontent.com/tikliz/hok_draft_utils/refs/heads/main/res/heros/Images/image_hero_head-Kaizer.png",
                "mainJob": 2,
                "recommendRoad": 1,
                "minorJob": 1,
                "mainJobName": "Guerreiro",
                "minorJobName": "Tanque",
                "recommendRoadName": "Rota superior",
                "firstTimeUpgradeSkill": 1,
                "cover": ""
            },
            {
                "heroId": 184,
                "heroName": "Cai Yan",
                "icon": "https://raw.githubusercontent.com/tikliz/hok_draft_utils/refs/heads/main/res/heros/Images/image_hero_head-Cai Yan.png",
                "mainJob": 6,
                "recommendRoad": 4,
                "minorJob": 0,
                "mainJobName": "Suporte",
                "minorJobName": "",
                "recommendRoadName": "Apoio",
                "firstTimeUpgradeSkill": 1,
                "cover": ""
            },
            {
                "heroId": 198,
                "heroName": "Menki",
                "icon": "https://raw.githubusercontent.com/tikliz/hok_draft_utils/refs/heads/main/res/heros/Images/image_hero_head-Menki.png",
                "mainJob": 2,
                "recommendRoad": 2,
                "minorJob": 4,
                "mainJobName": "Guerreiro",
                "minorJobName": "Mago",
                "recommendRoadName": "Caça",
                "firstTimeUpgradeSkill": 2,
                "cover": ""
            },
            {
                "heroId": 187,
                "heroName": "Donghuang",
                "icon": "https://raw.githubusercontent.com/tikliz/hok_draft_utils/refs/heads/main/res/heros/Images/image_hero_head-Donghuang.png",
                "mainJob": 6,
                "recommendRoad": 4,
                "minorJob": 1,
                "mainJobName": "Suporte",
                "minorJobName": "Tanque",
                "recommendRoadName": "Apoio",
                "firstTimeUpgradeSkill": 1,
                "cover": ""
            },
            {
                "heroId": 189,
                "heroName": "Guiguzi",
                "icon": "https://raw.githubusercontent.com/tikliz/hok_draft_utils/refs/heads/main/res/heros/Images/image_hero_head-Guiguzi.png",
                "mainJob": 6,
                "recommendRoad": 4,
                "minorJob": 0,
                "mainJobName": "Suporte",
                "minorJobName": "",
                "recommendRoadName": "Apoio",
                "firstTimeUpgradeSkill": 2,
                "cover": ""
            },
            {
                "heroId": 190,
                "heroName": "Kongming",
                "icon": "https://raw.githubusercontent.com/tikliz/hok_draft_utils/refs/heads/main/res/heros/Images/image_hero_head-Kongming.png",
                "mainJob": 4,
                "recommendRoad": 3,
                "minorJob": 0,
                "mainJobName": "Mago",
                "minorJobName": "",
                "recommendRoadName": "Rota do meio",
                "firstTimeUpgradeSkill": 2,
                "cover": ""
            },
            {
                "heroId": 191,
                "heroName": "Da Qiao",
                "icon": "https://raw.githubusercontent.com/tikliz/hok_draft_utils/refs/heads/main/res/heros/Images/image_hero_head-Da Qiao.png",
                "mainJob": 6,
                "recommendRoad": 4,
                "minorJob": 4,
                "mainJobName": "Suporte",
                "minorJobName": "Mago",
                "recommendRoadName": "Apoio",
                "firstTimeUpgradeSkill": 3,
                "cover": ""
            },
            {
                "heroId": 192,
                "heroName": "Huang Zhong",
                "icon": "https://raw.githubusercontent.com/tikliz/hok_draft_utils/refs/heads/main/res/heros/Images/image_hero_head-Huang Zhong.png",
                "mainJob": 5,
                "recommendRoad": 5,
                "minorJob": 0,
                "mainJobName": "Atirador",
                "minorJobName": "",
                "recommendRoadName": "Rota inferior",
                "firstTimeUpgradeSkill": 1,
                "cover": ""
            },
            {
                "heroId": 196,
                "heroName": "Shouyue",
                "icon": "https://raw.githubusercontent.com/tikliz/hok_draft_utils/refs/heads/main/res/heros/Images/image_hero_head-Shouyue.png",
                "mainJob": 5,
                "recommendRoad": 5,
                "minorJob": 3,
                "mainJobName": "Atirador",
                "minorJobName": "Assassino",
                "recommendRoadName": "Rota inferior",
                "firstTimeUpgradeSkill": 2,
                "cover": ""
            },
            {
                "heroId": 199,
                "heroName": "Arli",
                "icon": "https://raw.githubusercontent.com/tikliz/hok_draft_utils/refs/heads/main/res/heros/Images/image_hero_head-Arli.png",
                "mainJob": 5,
                "recommendRoad": 5,
                "minorJob": 0,
                "mainJobName": "Atirador",
                "minorJobName": "",
                "recommendRoadName": "Rota inferior",
                "firstTimeUpgradeSkill": 2,
                "cover": ""
            },
            {
                "heroId": 501,
                "heroName": "Ming",
                "icon": "https://raw.githubusercontent.com/tikliz/hok_draft_utils/refs/heads/main/res/heros/Images/image_hero_head-Ming.png",
                "mainJob": 6,
                "recommendRoad": 4,
                "minorJob": 0,
                "mainJobName": "Suporte",
                "minorJobName": "",
                "recommendRoadName": "Apoio",
                "firstTimeUpgradeSkill": 1,
                "cover": ""
            },
            {
                "heroId": 502,
                "heroName": "Pei",
                "icon": "https://raw.githubusercontent.com/tikliz/hok_draft_utils/refs/heads/main/res/heros/Images/image_hero_head-Pei.png",
                "mainJob": 3,
                "recommendRoad": 2,
                "minorJob": 2,
                "mainJobName": "Assassino",
                "minorJobName": "Guerreiro",
                "recommendRoadName": "Caça",
                "firstTimeUpgradeSkill": 2,
                "cover": ""
            },
            {
                "heroId": 504,
                "heroName": "Milady",
                "icon": "https://raw.githubusercontent.com/tikliz/hok_draft_utils/refs/heads/main/res/heros/Images/image_hero_head-Milady.png",
                "mainJob": 4,
                "recommendRoad": 3,
                "minorJob": 0,
                "mainJobName": "Mago",
                "minorJobName": "",
                "recommendRoadName": "Rota do meio",
                "firstTimeUpgradeSkill": 1,
                "cover": ""
            },
            {
                "heroId": 505,
                "heroName": "Yaria",
                "icon": "https://raw.githubusercontent.com/tikliz/hok_draft_utils/refs/heads/main/res/heros/Images/image_hero_head-Yaria.png",
                "mainJob": 6,
                "recommendRoad": 4,
                "minorJob": 0,
                "mainJobName": "Suporte",
                "minorJobName": "",
                "recommendRoadName": "Apoio",
                "firstTimeUpgradeSkill": 1,
                "cover": ""
            },
            {
                "heroId": 506,
                "heroName": "Cirrus",
                "icon": "https://raw.githubusercontent.com/tikliz/hok_draft_utils/refs/heads/main/res/heros/Images/image_hero_head-Cirrus.png",
                "mainJob": 3,
                "recommendRoad": 2,
                "minorJob": 2,
                "mainJobName": "Assassino",
                "minorJobName": "Guerreiro",
                "recommendRoadName": "Caça",
                "firstTimeUpgradeSkill": 2,
                "cover": ""
            },
            {
                "heroId": 507,
                "heroName": "Li Xin",
                "icon": "https://raw.githubusercontent.com/tikliz/hok_draft_utils/refs/heads/main/res/heros/Images/image_hero_head-Li Xin.png",
                "mainJob": 2,
                "recommendRoad": 1,
                "minorJob": 0,
                "mainJobName": "Guerreiro",
                "minorJobName": "",
                "recommendRoadName": "Rota superior",
                "firstTimeUpgradeSkill": 2,
                "cover": ""
            },
            {
                "heroId": 508,
                "heroName": "Garo",
                "icon": "https://raw.githubusercontent.com/tikliz/hok_draft_utils/refs/heads/main/res/heros/Images/image_hero_head-Garo.png",
                "mainJob": 5,
                "recommendRoad": 5,
                "minorJob": 0,
                "mainJobName": "Atirador",
                "minorJobName": "",
                "recommendRoadName": "Rota inferior",
                "firstTimeUpgradeSkill": 2,
                "cover": ""
            },
            {
                "heroId": 513,
                "heroName": "Shangguan",
                "icon": "https://raw.githubusercontent.com/tikliz/hok_draft_utils/refs/heads/main/res/heros/Images/image_hero_head-Shangguan.png",
                "mainJob": 4,
                "recommendRoad": 3,
                "minorJob": 3,
                "mainJobName": "Mago",
                "minorJobName": "Assassino",
                "recommendRoadName": "Rota do meio",
                "firstTimeUpgradeSkill": 1,
                "cover": ""
            },
            {
                "heroId": 646,
                "heroName": "Butterfly",
                "icon": "https://raw.githubusercontent.com/tikliz/hok_draft_utils/refs/heads/main/res/heros/Images/image_hero_head-Butterfly.png",
                "mainJob": 2,
                "recommendRoad": 2,
                "minorJob": 0,
                "mainJobName": "Guerreiro",
                "minorJobName": "",
                "recommendRoadName": "Caça",
                "firstTimeUpgradeSkill": 2,
                "cover": ""
            },
            {
                "heroId": 528,
                "heroName": "Lam",
                "icon": "https://raw.githubusercontent.com/tikliz/hok_draft_utils/refs/heads/main/res/heros/Images/image_hero_head-Lam.png",
                "mainJob": 3,
                "recommendRoad": 2,
                "minorJob": 0,
                "mainJobName": "Assassino",
                "minorJobName": "",
                "recommendRoadName": "Caça",
                "firstTimeUpgradeSkill": 2,
                "cover": ""
            },
            {
                "heroId": 531,
                "heroName": "Jing",
                "icon": "https://raw.githubusercontent.com/tikliz/hok_draft_utils/refs/heads/main/res/heros/Images/image_hero_head-Jing.png",
                "mainJob": 3,
                "recommendRoad": 2,
                "minorJob": 0,
                "mainJobName": "Assassino",
                "minorJobName": "",
                "recommendRoadName": "Caça",
                "firstTimeUpgradeSkill": 2,
                "cover": ""
            },
            {
                "heroId": 536,
                "heroName": "Charlotte",
                "icon": "https://raw.githubusercontent.com/tikliz/hok_draft_utils/refs/heads/main/res/heros/Images/image_hero_head-Charlotte.png",
                "mainJob": 2,
                "recommendRoad": 1,
                "minorJob": 0,
                "mainJobName": "Guerreiro",
                "minorJobName": "",
                "recommendRoadName": "Rota superior",
                "firstTimeUpgradeSkill": 1,
                "cover": ""
            },
            {
                "heroId": 538,
                "heroName": "Ying",
                "icon": "https://raw.githubusercontent.com/tikliz/hok_draft_utils/refs/heads/main/res/heros/Images/image_hero_head-Ying.png",
                "mainJob": 2,
                "recommendRoad": 2,
                "minorJob": 3,
                "mainJobName": "Guerreiro",
                "minorJobName": "Assassino",
                "recommendRoadName": "Caça",
                "firstTimeUpgradeSkill": 1,
                "cover": ""
            },
            {
                "heroId": 545,
                "heroName": "Alessio",
                "icon": "https://raw.githubusercontent.com/tikliz/hok_draft_utils/refs/heads/main/res/heros/Images/image_hero_head-Alessio.png",
                "mainJob": 5,
                "recommendRoad": 5,
                "minorJob": 0,
                "mainJobName": "Atirador",
                "minorJobName": "",
                "recommendRoadName": "Rota inferior",
                "firstTimeUpgradeSkill": 1,
                "cover": ""
            },
            {
                "heroId": 556,
                "heroName": "Ata",
                "icon": "https://raw.githubusercontent.com/tikliz/hok_draft_utils/refs/heads/main/res/heros/Images/image_hero_head-Ata.png",
                "mainJob": 1,
                "recommendRoad": 1,
                "minorJob": 0,
                "mainJobName": "Tanque",
                "minorJobName": "",
                "recommendRoadName": "Rota superior",
                "firstTimeUpgradeSkill": 1,
                "cover": ""
            },
            {
                "heroId": 159,
                "heroName": "Dolia",
                "icon": "https://raw.githubusercontent.com/tikliz/hok_draft_utils/refs/heads/main/res/heros/Images/image_hero_head-Dolia.png",
                "mainJob": 6,
                "recommendRoad": 4,
                "minorJob": 0,
                "mainJobName": "Suporte",
                "minorJobName": "",
                "recommendRoadName": "Apoio",
                "firstTimeUpgradeSkill": 1,
                "cover": ""
            },
            {
                "heroId": 547,
                "heroName": "Luara",
                "icon": "https://raw.githubusercontent.com/tikliz/hok_draft_utils/refs/heads/main/res/heros/Images/image_hero_head-Luara.png",
                "mainJob": 5,
                "recommendRoad": 5,
                "minorJob": 0,
                "mainJobName": "Atirador",
                "minorJobName": "",
                "recommendRoadName": "Rota inferior",
                "firstTimeUpgradeSkill": 2,
                "cover": ""
            },
            {
                "heroId": 519,
                "heroName": "Loong",
                "icon": "https://raw.githubusercontent.com/tikliz/hok_draft_utils/refs/heads/main/res/heros/Images/image_hero_head-Loong.jpg",
                "mainJob": 5,
                "recommendRoad": 5,
                "minorJob": 0,
                "mainJobName": "Atirador",
                "minorJobName": "",
                "recommendRoadName": "Rota inferior",
                "firstTimeUpgradeSkill": 1,
                "cover": ""
            },
            {
                "heroId": 128,
                "heroName": "Cao Cao",
                "icon": "https://raw.githubusercontent.com/tikliz/hok_draft_utils/refs/heads/main/res/heros/Images/image_hero_head-Cao Cao.png",
                "mainJob": 2,
                "recommendRoad": 1,
                "minorJob": 0,
                "mainJobName": "Guerreiro",
                "minorJobName": "",
                "recommendRoadName": "Rota superior",
                "firstTimeUpgradeSkill": 1,
                "cover": ""
            },
            {
                "heroId": 155,
                "heroName": "Erin",
                "icon": "https://raw.githubusercontent.com/tikliz/hok_draft_utils/refs/heads/main/res/heros/Images/image_hero_head-Erin.png",
                "mainJob": 5,
                "recommendRoad": 5,
                "minorJob": 0,
                "mainJobName": "Atirador",
                "minorJobName": "",
                "recommendRoadName": "Rota inferior",
                "firstTimeUpgradeSkill": 1,
                "cover": ""
            },
            {
                "heroId": 514,
                "heroName": "Allain",
                "icon": "https://raw.githubusercontent.com/tikliz/hok_draft_utils/refs/heads/main/res/heros/Images/image_hero_head-Allain.png",
                "mainJob": 2,
                "recommendRoad": 1,
                "minorJob": 0,
                "mainJobName": "Guerreiro",
                "minorJobName": "",
                "recommendRoadName": "Rota superior",
                "firstTimeUpgradeSkill": 1,
                "cover": ""
            },
            {
                "heroId": 510,
                "heroName": "Sun Ce",
                "icon": "https://raw.githubusercontent.com/tikliz/hok_draft_utils/refs/heads/main/res/heros/Images/image_hero_head-Sun Ce.png",
                "mainJob": 2,
                "recommendRoad": 1,
                "minorJob": 1,
                "mainJobName": "Guerreiro",
                "minorJobName": "Tanque",
                "recommendRoadName": "Rota superior",
                "firstTimeUpgradeSkill": 2,
                "cover": ""
            },
            {
                "heroId": 564,
                "heroName": "Mayene",
                "icon": "https://raw.githubusercontent.com/tikliz/hok_draft_utils/refs/heads/main/res/heros/Images/image_hero_head-Mayene.png",
                "mainJob": 2,
                "recommendRoad": 1,
                "minorJob": 0,
                "mainJobName": "Guerreiro",
                "minorJobName": "",
                "recommendRoadName": "Rota superior",
                "firstTimeUpgradeSkill": 1,
                "cover": ""
            },
            {
                "heroId": 563,
                "heroName": "Heino",
                "icon": "https://raw.githubusercontent.com/tikliz/hok_draft_utils/refs/heads/main/res/heros/Images/image_hero_head-Heino.png",
                "mainJob": 4,
                "recommendRoad": 3,
                "minorJob": 0,
                "mainJobName": "Mago",
                "minorJobName": "",
                "recommendRoadName": "Rota do meio",
                "firstTimeUpgradeSkill": 1,
                "cover": ""
            }
        ]
    }
}